{
    "cansaizuopin": [{
        "img": "./images/tupian/图层 42.png",
        "name": "2019 风尚引领奖",
        "author": "—— 阿杜 李维维"
    }, {
        "img": "./images/tupian/图层 42.png",
        "name": "2019 风尚引领奖",
        "author": "—— 阿杜 李维维"
    }, {
        "img": "./images/tupian/图层 42.png",
        "name": "2019 风尚引领奖",
        "author": "—— 阿杜 李维维"
    }, {
        "img": "./images/tupian/图层 42.png",
        "name": "2019 风尚引领奖",
        "author": "—— 阿杜 李维维"
    }, {
        "img": "./images/tupian/图层 42.png",
        "name": "2019 风尚引领奖",
        "author": "—— 阿杜 李维维"
    }, {
        "img": "./images/tupian/图层 42.png",
        "name": "2019 风尚引领奖",
        "author": "—— 阿杜 李维维"
    }, {
        "img": "./images/tupian/图层 42.png",
        "name": "2019 风尚引领奖",
        "author": "—— 阿杜 李维维"
    }, {
        "img": "./images/tupian/图层 42.png",
        "name": "2019 风尚引领奖",
        "author": "—— 阿杜 李维维"
    }, {
        "img": "./images/tupian/图层 42.png",
        "name": "2019 风尚引领奖",
        "author": "—— 阿杜 李维维"
    }, {
        "img": "./images/tupian/图层 42.png",
        "name": "2019 风尚引领奖",
        "author": "—— 阿杜 李维维"
    }, {
        "img": "./images/tupian/图层 42.png",
        "name": "2019 风尚引领奖",
        "author": "—— 阿杜 李维维"
    }, {
        "img": "./images/tupian/图层 42.png",
        "name": "2019 风尚引领奖",
        "author": "—— 阿杜 李维维"
    }]

}